gilbert/__init__.py
gilbert/__main__.py
gilbert/cli.py
gilbert/collection.py
gilbert/content.py
gilbert/exceptions.py
gilbert/query.py
gilbert/schema.py
gilbert/server.py
gilbert/site.py
gilbert/types.py
gilbert/plugins/__init__.py
gilbert/plugins/markdown.py
gilbert/plugins/scss.py
gilbert/plugins/selection.py
gilbert/plugins/yaml.py
gilbert-0.6.1.dist-info/LICENSE
gilbert-0.6.1.dist-info/METADATA
gilbert-0.6.1.dist-info/WHEEL
gilbert-0.6.1.dist-info/entry_points.txt
gilbert-0.6.1.dist-info/top_level.txt
gilbert-0.6.1.dist-info/RECORD
