Metadata-Version: 2.1
Name: gilbert
Version: 0.6.1
Summary: A simple, extensible static site generator.
Author-email: Curtis Maloney <curtis@tinbrain.net>
License: MIT
Project-URL: Documentation, https://gilbert.readthedocs.io/en/latest/
Project-URL: Source Code, https://github.com/funkybob/gilbert
Requires-Python: >=3.12
License-File: LICENSE
Requires-Dist: bareasgi-static
Requires-Dist: bareasgi
Requires-Dist: libsass
Requires-Dist: markdown
Requires-Dist: pyyaml
Requires-Dist: stencil-template
Requires-Dist: uvicorn
Requires-Dist: watchfiles
Provides-Extra: dev
Requires-Dist: coverage ; extra == 'dev'
Requires-Dist: mypy ; extra == 'dev'
Requires-Dist: pytest-mock ; extra == 'dev'
Requires-Dist: pytest ; extra == 'dev'
Requires-Dist: ruff ; extra == 'dev'
Requires-Dist: sphinx ; extra == 'dev'
